setup.py
theanify/__init__.py
theanify/theanify.py
theanify.egg-info/PKG-INFO
theanify.egg-info/SOURCES.txt
theanify.egg-info/dependency_links.txt
theanify.egg-info/requires.txt
theanify.egg-info/top_level.txt