Metadata-Version: 1.1
Name: theanify
Version: 0.0.5
Summary: Allows you to annotate instance methods to be compiled by Theano.
Home-page: https://github.com/sharadmv/theanify
Author: Sharad Vikram
Author-email: sharad.vikram@gmail.com
License: MIT
Keywords: theano
Platform: UNKNOWN
Classifier: Development Status :: 3 - Alpha
Classifier: Intended Audience :: Developers
Classifier: Topic :: Software Development :: Build Tools
Classifier: License :: OSI Approved :: MIT License
Classifier: Programming Language :: Python :: 2.7
